examples/__init__.py
examples/basic_example_node.py
examples/basic_pipeline.py
examples/mnist_pipeline.py
examples/newsgroups_pipeline.py
fastpipeline/Utils.py
fastpipeline/__init__.py
fastpipeline/base_node.py
fastpipeline/pipeline.py
tests/__init__.py
tests/test_data_types.py
fastpipeline-0.0.2.dist-info/METADATA
fastpipeline-0.0.2.dist-info/WHEEL
fastpipeline-0.0.2.dist-info/top_level.txt
fastpipeline-0.0.2.dist-info/RECORD
