Metadata-Version: 2.1
Name: fastpipeline
Version: 0.0.2
Summary: Build time saving ML pipelines with built in autosave and reload
Home-page: https://github.com/shashank-yadav/fastpipeline
Author: Shashank Yadav
Author-email: shashank7.iitd@gmail.com
License: UNKNOWN
Platform: UNKNOWN
Classifier: Programming Language :: Python :: 3
Classifier: License :: OSI Approved :: MIT License
Classifier: Operating System :: OS Independent
Requires-Python: >=3.7.4
